{
  "name": "Gillean Jordan",
  "gender": "Female",
  "affiliation": "N54 News",
  "description": "In2077, she gives a live report of the assault that was made during theArasakadashi parade taking place inJapantown,Westbrook. She can also be seen withArif Iqbalin theBlack SapphireduringYou Know My Name. Afterwards, she can be found doing a news report just inside ofNight City International and TranslunarduringThe Killing Moon.",
  "has_images": true,
  "wiki_url": "https://cyberpunk.fandom.com/wiki/Gillean_Jordan",
  "occupation": "Media",
  "status": "Alive"
}