{
  "name": "Annie Capolino",
  "gender": "Female",
  "affiliation": "Forlorn Hope",
  "description": "Trigger is a young woman who helpsIcepickwith security at the bar. She's a Solo specializing in security penetration and stealth operations. She frequently takes leaves of absence from the bar to run Jobs for clients. Trigger is something of an expert on the local crime scene. I was told to ask her if I had any questions about local gangs or crime outfits. Trigger spends a lot of her time withDollar Bill, although no one seems clear on their relationship; neither would talk about it. Trigger, like her associate, is a permanent resident of the Hotel Sierra building. She lives in a third-floor...",
  "has_images": false,
  "wiki_url": "https://cyberpunk.fandom.com/wiki/Annie_Capolino",
  "occupation": "Solo",
  "status": "Alive (2020)"
}