{"batchcomplete": "", "query": {"normalized": [{"from": "File:Lina_Malina_Poster_CP2077PL.png", "to": "File:Lina Malina Poster CP2077PL.png"}], "pages": {"35633": {"pageid": 35633, "ns": 6, "title": "File:Lina Malina Poster CP2077PL.png", "imagerepository": "local", "imageinfo": [{"url": "https://static.wikia.nocookie.net/cyberpunk/images/6/68/Lina_Malina_Poster_CP2077PL.png/revision/latest?cb=20240614135522", "descriptionurl": "https://cyberpunk.fandom.com/wiki/File:Lina_Malina_Poster_CP2077PL.png", "descriptionshorturl": "https://cyberpunk.fandom.com/index.php?curid=35633"}]}}}}