{"batchcomplete": "", "query": {"normalized": [{"from": "File:Char_Profile_Denzel_Cryer.jpg", "to": "File:Char Profile Denzel Cryer.jpg"}], "pages": {"29112": {"pageid": 29112, "ns": 6, "title": "File:Char Profile Denzel Cryer.jpg", "imagerepository": "local", "imageinfo": [{"url": "https://static.wikia.nocookie.net/cyberpunk/images/6/63/Char_Profile_Denzel_Cryer.jpg/revision/latest?cb=20230615230444", "descriptionurl": "https://cyberpunk.fandom.com/wiki/File:Char_Profile_Denzel_Cryer.jpg", "descriptionshorturl": "https://cyberpunk.fandom.com/index.php?curid=29112"}]}}}}