{"continue": {"iistart": "2022-06-08T12:29:20Z", "continue": "||"}, "query": {"normalized": [{"from": "File:Rhino_HoNC_CP2077.jpg", "to": "File:Rhino HoNC CP2077.jpg"}], "pages": {"24441": {"pageid": 24441, "ns": 6, "title": "File:Rhino HoNC CP2077.jpg", "imagerepository": "local", "imageinfo": [{"url": "https://static.wikia.nocookie.net/cyberpunk/images/0/04/Rhino_HoNC_CP2077.jpg/revision/latest?cb=20220612141132", "descriptionurl": "https://cyberpunk.fandom.com/wiki/File:Rhino_HoNC_CP2077.jpg", "descriptionshorturl": "https://cyberpunk.fandom.com/index.php?curid=24441"}]}}}}